<?xml version="1.0" encoding="UTF-8"?>
<DEFECTS>
  <DEFECT>
    <SFA>
      <FILEPATH>h:\year 2 v2\secure software\assignment 2\036\ssd_cs2s562</FILEPATH>
      <FILENAME>electric.cpp</FILENAME>
      <LINE>4</LINE>
      <COLUMN>10</COLUMN>
    </SFA>
    <DEFECTCODE>26495</DEFECTCODE>
    <DESCRIPTION>Variable 'Electric::average' is uninitialized. Always initialize a member variable (type.6).</DESCRIPTION>
    <FUNCTION>Electric::{ctor}</FUNCTION>
    <DECORATED>??0Electric@@QAE@XZ</DECORATED>
    <FUNCLINE>4</FUNCLINE>
    <PATH></PATH>
  </DEFECT>
  <DEFECT>
    <SFA>
      <FILEPATH>h:\year 2 v2\secure software\assignment 2\036\ssd_cs2s562</FILEPATH>
      <FILENAME>electric.cpp</FILENAME>
      <LINE>4</LINE>
      <COLUMN>10</COLUMN>
    </SFA>
    <DEFECTCODE>26455</DEFECTCODE>
    <DESCRIPTION>Default constructor may not throw. Declare it 'noexcept' (f.6).</DESCRIPTION>
    <FUNCTION>Electric::{ctor}</FUNCTION>
    <DECORATED>??0Electric@@QAE@XZ</DECORATED>
    <FUNCLINE>4</FUNCLINE>
    <PATH></PATH>
  </DEFECT>
  <DEFECT>
    <SFA>
      <FILEPATH>h:\year 2 v2\secure software\assignment 2\036\ssd_cs2s562</FILEPATH>
      <FILENAME>electric.cpp</FILENAME>
      <LINE>8</LINE>
      <COLUMN>38</COLUMN>
    </SFA>
    <DEFECTCODE>26477</DEFECTCODE>
    <DESCRIPTION>Use 'nullptr' rather than 0 or NULL (es.47).</DESCRIPTION>
    <FUNCTION>Electric::populate</FUNCTION>
    <DECORATED>?populate@Electric@@QAEXXZ</DECORATED>
    <FUNCLINE>6</FUNCLINE>
    <PATH></PATH>
  </DEFECT>
  <DEFECT>
    <SFA>
      <FILEPATH>h:\year 2 v2\secure software\assignment 2\036\ssd_cs2s562</FILEPATH>
      <FILENAME>electric.cpp</FILENAME>
      <LINE>8</LINE>
      <COLUMN>6</COLUMN>
    </SFA>
    <DEFECTCODE>26472</DEFECTCODE>
    <DESCRIPTION>Don't use a static_cast for arithmetic conversions. Use brace initialization, gsl::narrow_cast or gsl::narrow (type.1).</DESCRIPTION>
    <FUNCTION>Electric::populate</FUNCTION>
    <DECORATED>?populate@Electric@@QAEXXZ</DECORATED>
    <FUNCLINE>6</FUNCLINE>
    <PATH></PATH>
  </DEFECT>
  <DEFECT>
    <SFA>
      <FILEPATH>h:\year 2 v2\secure software\assignment 2\036\ssd_cs2s562</FILEPATH>
      <FILENAME>electric.cpp</FILENAME>
      <LINE>23</LINE>
      <COLUMN>6</COLUMN>
    </SFA>
    <DEFECTCODE>26496</DEFECTCODE>
    <DESCRIPTION>The variable 'x' is assigned only once, mark it as const (con.4).</DESCRIPTION>
    <FUNCTION>Electric::getData</FUNCTION>
    <DECORATED>?getData@Electric@@QAEXXZ</DECORATED>
    <FUNCLINE>18</FUNCLINE>
    <PATH></PATH>
  </DEFECT>
  <DEFECT>
    <SFA>
      <FILEPATH>h:\year 2 v2\secure software\assignment 2\036\ssd_cs2s562</FILEPATH>
      <FILENAME>electric.cpp</FILENAME>
      <LINE>23</LINE>
      <COLUMN>17</COLUMN>
    </SFA>
    <DEFECTCODE>26446</DEFECTCODE>
    <DESCRIPTION>Prefer to use gsl::at() instead of unchecked subscript operator (bounds.4).</DESCRIPTION>
    <FUNCTION>Electric::getData</FUNCTION>
    <DECORATED>?getData@Electric@@QAEXXZ</DECORATED>
    <FUNCLINE>18</FUNCLINE>
    <PATH></PATH>
  </DEFECT>
  <DEFECT>
    <SFA>
      <FILEPATH>h:\year 2 v2\secure software\assignment 2\036\ssd_cs2s562</FILEPATH>
      <FILENAME>electric.cpp</FILENAME>
      <LINE>23</LINE>
      <COLUMN>28</COLUMN>
    </SFA>
    <DEFECTCODE>26446</DEFECTCODE>
    <DESCRIPTION>Prefer to use gsl::at() instead of unchecked subscript operator (bounds.4).</DESCRIPTION>
    <FUNCTION>Electric::getData</FUNCTION>
    <DECORATED>?getData@Electric@@QAEXXZ</DECORATED>
    <FUNCLINE>18</FUNCLINE>
    <PATH></PATH>
  </DEFECT>
  <DEFECT>
    <SFA>
      <FILEPATH>h:\year 2 v2\secure software\assignment 2\036\ssd_cs2s562</FILEPATH>
      <FILENAME>electric.cpp</FILENAME>
      <LINE>23</LINE>
      <COLUMN>39</COLUMN>
    </SFA>
    <DEFECTCODE>26446</DEFECTCODE>
    <DESCRIPTION>Prefer to use gsl::at() instead of unchecked subscript operator (bounds.4).</DESCRIPTION>
    <FUNCTION>Electric::getData</FUNCTION>
    <DECORATED>?getData@Electric@@QAEXXZ</DECORATED>
    <FUNCLINE>18</FUNCLINE>
    <PATH></PATH>
  </DEFECT>
  <DEFECT>
    <SFA>
      <FILEPATH>h:\year 2 v2\secure software\assignment 2\036\ssd_cs2s562</FILEPATH>
      <FILENAME>electric.cpp</FILENAME>
      <LINE>23</LINE>
      <COLUMN>50</COLUMN>
    </SFA>
    <DEFECTCODE>26446</DEFECTCODE>
    <DESCRIPTION>Prefer to use gsl::at() instead of unchecked subscript operator (bounds.4).</DESCRIPTION>
    <FUNCTION>Electric::getData</FUNCTION>
    <DECORATED>?getData@Electric@@QAEXXZ</DECORATED>
    <FUNCLINE>18</FUNCLINE>
    <PATH></PATH>
  </DEFECT>
  <DEFECT>
    <SFA>
      <FILEPATH>h:\year 2 v2\secure software\assignment 2\036\ssd_cs2s562</FILEPATH>
      <FILENAME>electric.cpp</FILENAME>
      <LINE>38</LINE>
      <COLUMN>32</COLUMN>
    </SFA>
    <DEFECTCODE>26446</DEFECTCODE>
    <DESCRIPTION>Prefer to use gsl::at() instead of unchecked subscript operator (bounds.4).</DESCRIPTION>
    <FUNCTION>Electric::save</FUNCTION>
    <DECORATED>?save@Electric@@QAEXXZ</DECORATED>
    <FUNCLINE>30</FUNCLINE>
    <PATH></PATH>
  </DEFECT>
  <DEFECT>
    <SFA>
      <FILEPATH>h:\year 2 v2\secure software\assignment 2\036\ssd_cs2s562</FILEPATH>
      <FILENAME>electric.cpp</FILENAME>
      <LINE>53</LINE>
      <COLUMN>56</COLUMN>
    </SFA>
    <DEFECTCODE>26446</DEFECTCODE>
    <DESCRIPTION>Prefer to use gsl::at() instead of unchecked subscript operator (bounds.4).</DESCRIPTION>
    <FUNCTION>Electric::print</FUNCTION>
    <DECORATED>?print@Electric@@QAEXXZ</DECORATED>
    <FUNCLINE>49</FUNCLINE>
    <PATH></PATH>
  </DEFECT>
  <DEFECT>
    <SFA>
      <FILEPATH>h:\year 2 v2\secure software\assignment 2\036\ssd_cs2s562</FILEPATH>
      <FILENAME>electric.cpp</FILENAME>
      <LINE>54</LINE>
      <COLUMN>53</COLUMN>
    </SFA>
    <DEFECTCODE>26446</DEFECTCODE>
    <DESCRIPTION>Prefer to use gsl::at() instead of unchecked subscript operator (bounds.4).</DESCRIPTION>
    <FUNCTION>Electric::print</FUNCTION>
    <DECORATED>?print@Electric@@QAEXXZ</DECORATED>
    <FUNCLINE>49</FUNCLINE>
    <PATH></PATH>
  </DEFECT>
  <DEFECT>
    <SFA>
      <FILEPATH>h:\year 2 v2\secure software\assignment 2\036\ssd_cs2s562</FILEPATH>
      <FILENAME>electric.cpp</FILENAME>
      <LINE>55</LINE>
      <COLUMN>53</COLUMN>
    </SFA>
    <DEFECTCODE>26446</DEFECTCODE>
    <DESCRIPTION>Prefer to use gsl::at() instead of unchecked subscript operator (bounds.4).</DESCRIPTION>
    <FUNCTION>Electric::print</FUNCTION>
    <DECORATED>?print@Electric@@QAEXXZ</DECORATED>
    <FUNCLINE>49</FUNCLINE>
    <PATH></PATH>
  </DEFECT>
  <DEFECT>
    <SFA>
      <FILEPATH>h:\year 2 v2\secure software\assignment 2\036\ssd_cs2s562</FILEPATH>
      <FILENAME>electric.cpp</FILENAME>
      <LINE>56</LINE>
      <COLUMN>54</COLUMN>
    </SFA>
    <DEFECTCODE>26446</DEFECTCODE>
    <DESCRIPTION>Prefer to use gsl::at() instead of unchecked subscript operator (bounds.4).</DESCRIPTION>
    <FUNCTION>Electric::print</FUNCTION>
    <DECORATED>?print@Electric@@QAEXXZ</DECORATED>
    <FUNCLINE>49</FUNCLINE>
    <PATH></PATH>
  </DEFECT>
  <DEFECT>
    <SFA>
      <FILEPATH>h:\year 2 v2\secure software\assignment 2\036\ssd_cs2s562</FILEPATH>
      <FILENAME>electric.cpp</FILENAME>
      <LINE>58</LINE>
      <COLUMN>61</COLUMN>
    </SFA>
    <DEFECTCODE>26446</DEFECTCODE>
    <DESCRIPTION>Prefer to use gsl::at() instead of unchecked subscript operator (bounds.4).</DESCRIPTION>
    <FUNCTION>Electric::print</FUNCTION>
    <DECORATED>?print@Electric@@QAEXXZ</DECORATED>
    <FUNCLINE>49</FUNCLINE>
    <PATH></PATH>
  </DEFECT>
  <DEFECT>
    <SFA>
      <FILEPATH>h:\year 2 v2\secure software\assignment 2\036\ssd_cs2s562</FILEPATH>
      <FILENAME>electric.cpp</FILENAME>
      <LINE>86</LINE>
      <COLUMN>31</COLUMN>
    </SFA>
    <DEFECTCODE>26446</DEFECTCODE>
    <DESCRIPTION>Prefer to use gsl::at() instead of unchecked subscript operator (bounds.4).</DESCRIPTION>
    <FUNCTION>Electric::print</FUNCTION>
    <DECORATED>?print@Electric@@QAEXXZ</DECORATED>
    <FUNCLINE>49</FUNCLINE>
    <PATH></PATH>
  </DEFECT>
  <DEFECT>
    <SFA>
      <FILEPATH>h:\year 2 v2\secure software\assignment 2\036\ssd_cs2s562</FILEPATH>
      <FILENAME>electric.cpp</FILENAME>
      <LINE>112</LINE>
      <COLUMN>14</COLUMN>
    </SFA>
    <DEFECTCODE>26446</DEFECTCODE>
    <DESCRIPTION>Prefer to use gsl::at() instead of unchecked subscript operator (bounds.4).</DESCRIPTION>
    <FUNCTION>Electric::getElec</FUNCTION>
    <DECORATED>?getElec@Electric@@QAEHH@Z</DECORATED>
    <FUNCLINE>108</FUNCLINE>
    <PATH></PATH>
  </DEFECT>
</DEFECTS>